alembic.ini
rms_models/__init__.py
rms_models/database.py
rms_models/migrate.py
rms_models/models.py
rms_models-0.1.5.dist-info/entry_points.txt
rms_models-0.1.5.dist-info/METADATA
rms_models-0.1.5.dist-info/WHEEL
rms_models-0.1.5.dist-info/RECORD
